<annotation>
	<folder>collectedimages</folder>
	<filename>yes.01adf16e-6497-11eb-a3be-f0038cf359fa.jpg</filename>
	<path>C:\Users\timaz\Desktop\MyDiplomaProject\Tensorflow\workspace\images\collectedimages\yes.01adf16e-6497-11eb-a3be-f0038cf359fa.jpg</path>
	<source>
		<database>Unknown</database>
	</source>
	<size>
		<width>640</width>
		<height>480</height>
		<depth>3</depth>
	</size>
	<segmented>0</segmented>
	<object>
		<name>Yes</name>
		<pose>Unspecified</pose>
		<truncated>0</truncated>
		<difficult>0</difficult>
		<bndbox>
			<xmin>237</xmin>
			<ymin>177</ymin>
			<xmax>412</xmax>
			<ymax>295</ymax>
		</bndbox>
	</object>
</annotation>
